SuperQQBot/__init__.py
SuperQQBot/core/Error.py
SuperQQBot/core/User_Interface.py
SuperQQBot/core/__init__.py
SuperQQBot/core/api.py
SuperQQBot/core/client.py
SuperQQBot/core/connection.py
SuperQQBot/core/logging.py
SuperQQBot/core/types.py
SuperQQBot/ext/ModLoaderCoreSupport.py
SuperQQBot/ext/__init__.py
SuperQQBot/ext/cog_yaml.py
SuperQQBot-2024.11.30.0.dist-info/LICENSE
SuperQQBot-2024.11.30.0.dist-info/METADATA
SuperQQBot-2024.11.30.0.dist-info/WHEEL
SuperQQBot-2024.11.30.0.dist-info/top_level.txt
SuperQQBot-2024.11.30.0.dist-info/RECORD
