Metadata-Version: 2.1
Name: SuperQQBot
Version: 2024.11.30.0
Summary: 新一代QQ机器人SDK
Home-page: https://gitee.com/SuperQQBot/SuperQQBot
Author: Supercmd
Author-email: trustedinster@outlook.com
License: GNU General Public License v2.0 (GPL2.0)
Classifier: Development Status :: 3 - Alpha
Classifier: Intended Audience :: Developers
Classifier: License :: OSI Approved :: GNU General Public License v2 (GPLv2)
Classifier: Programming Language :: Python :: 3
Classifier: Programming Language :: Python :: 3.6
Classifier: Programming Language :: Python :: 3.7
Classifier: Programming Language :: Python :: 3.8
Classifier: Programming Language :: Python :: 3.9
Classifier: Programming Language :: Python :: 3.10
Requires-Python: >=3.8
License-File: LICENSE
Requires-Dist: asyncio~=3.4.3
Requires-Dist: PyYAML~=6.0.2
Requires-Dist: python-dateutil~=2.9.0.post0
Requires-Dist: requests~=2.32.3
Requires-Dist: charset-normalizer<4,>=2
Requires-Dist: idna<4,>=2.5
Requires-Dist: urllib3<3,>=1.21.1
Requires-Dist: certifi>=2017.4.17
Requires-Dist: pytz~=2024.2
Requires-Dist: datetime~=5.5
Requires-Dist: bottle~=0.13.2
